autoglyphs/__init__.py
autoglyphs/autoglyphs.py
autoglyphs-0.1.0.dist-info/LICENSE
autoglyphs-0.1.0.dist-info/WHEEL
autoglyphs-0.1.0.dist-info/METADATA
autoglyphs-0.1.0.dist-info/RECORD
