Metadata-Version: 2.1
Name: autoglyphs
Version: 0.1.0
Summary: 
Author: j1c
Author-email: jaewonc78@gmail.com
Requires-Python: >=3.8,<4.0
Classifier: Programming Language :: Python :: 3
Classifier: Programming Language :: Python :: 3.8
Classifier: Programming Language :: Python :: 3.9
Requires-Dist: matplotlib (>=3.4.3,<4.0.0)
Requires-Dist: web3 (>=5.23.0,<6.0.0)
